Metadata-Version: 2.1
Name: odoo-addon-account_brand
Version: 18.0.1.0.1.2
Requires-Python: >=3.10
Requires-Dist: odoo-addon-brand==18.0.*
Requires-Dist: odoo==18.0.*
Summary: Send branded invoices and refunds
Home-page: https://github.com/OCA/brand
License: AGPL-3
Author: Open Source Integrators,ACSONE SA/NV,Odoo Community Association (OCA)
Author-email: support@odoo-community.org
Classifier: Programming Language :: Python
Classifier: Framework :: Odoo
Classifier: Framework :: Odoo :: 18.0
Classifier: License :: OSI Approved :: GNU Affero General Public License v3
Classifier: Development Status :: 4 - Beta
